{"options":{"tileSet":{},"width":12,"height":12},"obj":{},"joObject":"TileMap","call":{},"width":12,"height":12,"data":[{"index":0},{"index":0},{"index":0},{"index":0},{"index":0},{"index":0},{"index":0},{"index":0},{"index":-1},{"index":-1},{"index":-1},{"index":-1},{"index":1},{"index":1},{"index":1},{"index":1},{"index":-1},{"index":-1},{"index":0},{"index":0},{"index":-1},{"index":-1},{"index":-1},{"index":-1},{"index":1},{"index":1},{"index":1},{"index":1},{"index":-1},{"index":-1},{"index":-1},{"index":0},{"index":-1},{"index":-1},{"index":-1},{"index":-1},{"index":1},{"index":1},{"index":1},{"index":1},{"index":-1},{"index":-1},{"index":-1},{"index":0},{"index":-1},{"index":-1},{"index":0},{"index":-1},{"index":-1},{"index":-1},{"index":-1},{"index":1},{"index":-1},{"index":-1},{"index":-1},{"index":0},{"index":-1},{"index":-1},{"index":0},{"index":-1},{"index":-1},{"index":-1},{"index":-1},{"index":-1},{"index":-1},{"index":-1},{"index":-1},{"index":0},{"index":-1},{"index":-1},{"index":0},{"index":-1},{"index":-1},{"index":-1},{"index":-1},{"index":-1},{"index":-1},{"index":-1},{"index":-1},{"index":-1},{"index":-1},{"index":-1},{"index":-1},{"index":-1},{"index":-1},{"index":-1},{"index":2},{"index":2},{"index":2},{"index":2},{"index":2},{"index":2},{"index":2},{"index":2},{"index":2},{"index":-1},{"index":-1},{"index":-1},{"index":-1},{"index":-1},{"index":-1},{"index":-1},{"index":-1},{"index":-1},{"index":2},{"index":-1},{"index":-1},{"index":-1},{"index":-1},{"index":-1},{"index":-1},{"index":-1},{"index":-1},{"index":2},{"index":2},{"index":2},{"index":2},{"index":0},{"index":0},{"index":0},{"index":-1},{"index":-1},{"index":-1},{"index":-1},{"index":-1},{"index":-1},{"index":-1},{"index":-1},{"index":-1},{"index":-1},{"index":-1},{"index":-1},{"index":-1},{"index":-1},{"index":-1},{"index":-1},{"index":-1},{"index":-1},{"index":-1},{"index":-1},{"index":-1},{"index":-1},{"index":-1},{"index":-1}],"tileSet":{}}